__init__.py
mmenot/__init__.py
mmenot/exporter.py
mmenot/hyp_searcher.py
mmenot/labels.py
mmenot/patches.py
mmenot/pruner.py
mmenot/runner.py
mmenot/tester.py
mmenot/trainer.py
mmenot/loops/__init__.py
mmenot/loops/epoch_optuna.py
mmenot/loops/epoch_pruning.py
mmenot/utils/__init__.py
mmenot/utils/common.py
mmenot/utils/hpo.py
mmenot-0.9.5.dist-info/LICENSE
mmenot-0.9.5.dist-info/METADATA
mmenot-0.9.5.dist-info/WHEEL
mmenot-0.9.5.dist-info/entry_points.txt
mmenot-0.9.5.dist-info/top_level.txt
mmenot-0.9.5.dist-info/RECORD
