Metadata-Version: 2.1
Name: mmenot
Version: 0.9.5
Summary: ENOT Framework integration package for OpenMMLab codebase
Author-email: ENOT LLC <enot@enot.ai>
License: Apache License
Project-URL: homepage, https://enot.ai
Project-URL: documentation, https://enot-autodl.rtd.enot.ai/en/latest/openmmlab/mmenot.html
Keywords: AI,ENOT,Pruning,MMDetection,MMSegmentation
Classifier: Development Status :: 5 - Production/Stable
Classifier: License :: OSI Approved :: Apache Software License
Classifier: Programming Language :: Python
Classifier: Programming Language :: Python :: 3.8
Classifier: Programming Language :: Python :: 3.9
Classifier: Programming Language :: Python :: 3 :: Only
Requires-Python: >=3.8
License-File: LICENSE
Requires-Dist: mmengine (>=0.7.2)
Requires-Dist: mmcv (>=2.0.0)
Requires-Dist: mmdeploy (>=1.0.0)
Requires-Dist: mmrazor (>=1.0.0)
Requires-Dist: onnx
Requires-Dist: numpy
Requires-Dist: enot-latency-server
Requires-Dist: enot-autodl
Requires-Dist: optuna
Provides-Extra: dev
Requires-Dist: black ; extra == 'dev'
Requires-Dist: pylint ; extra == 'dev'
Requires-Dist: pre-commit ; extra == 'dev'
Requires-Dist: isort ; extra == 'dev'
Provides-Extra: mmdet
Requires-Dist: mmdet (>=3.0.0) ; extra == 'mmdet'
Provides-Extra: mmseg
Requires-Dist: mmsegmentation (>=1.0.0) ; extra == 'mmseg'
